abbrs/__init__.py
abbrs-0.0.15.dist-info/METADATA
abbrs-0.0.15.dist-info/WHEEL
abbrs-0.0.15.dist-info/top_level.txt
abbrs-0.0.15.dist-info/RECORD
