Metadata-Version: 2.1
Name: abbrs
Version: 0.0.15
Summary: Abbreviations
Home-page: https://gitee.com/yanhuihang/abbrs
Author: YAN Hui Hang, GDUFS
Author-email: yanhuihang@126.com
License: UNKNOWN
Platform: UNKNOWN
Classifier: Programming Language :: Python :: 3
Classifier: Operating System :: OS Independent
Requires-Python: >=3.6
